MANIFEST.in
README.md
setup.py
bin/git-openaps-init
bin/openaps
bin/openaps-alias
bin/openaps-device
bin/openaps-import
bin/openaps-install-udev-rules
bin/openaps-report
bin/openaps-use
bin/openaps-vendor
openaps/__init__.py
openaps/builtins.py
openaps/config.py
openaps/configurable.py
openaps/init.py
openaps.egg-info/PKG-INFO
openaps.egg-info/SOURCES.txt
openaps.egg-info/dependency_links.txt
openaps.egg-info/entry_points.txt
openaps.egg-info/not-zip-safe
openaps.egg-info/requires.txt
openaps.egg-info/top_level.txt
openaps/alias/__init__.py
openaps/alias/add.py
openaps/alias/alias.py
openaps/alias/remove.py
openaps/alias/show.py
openaps/cli/__init__.py
openaps/cli/commandmapapp.py
openaps/cli/helpers.py
openaps/cli/subcommand.py
openaps/controllers/__init__.py
openaps/devices/__init__.py
openaps/devices/add.py
openaps/devices/device.py
openaps/devices/remove.py
openaps/devices/show.py
openaps/glucose/__init__.py
openaps/glucose/convert.py
openaps/glucose/display.py
openaps/monitors/__init__.py
openaps/reports/__init__.py
openaps/reports/add.py
openaps/reports/invoke.py
openaps/reports/remove.py
openaps/reports/report.py
openaps/reports/show.py
openaps/reports/reporters/JSON.py
openaps/reports/reporters/__init__.py
openaps/reports/reporters/base.py
openaps/reports/reporters/stdout.py
openaps/reports/reporters/text.py
openaps/suggesters/__init__.py
openaps/uses/__init__.py
openaps/uses/registry.py
openaps/uses/use.py
openaps/vendors/__init__.py
openaps/vendors/dexcom.py
openaps/vendors/medtronic.py
openaps/vendors/process.py
openaps/vendors/units.py
openaps/vendors/plugins/__init__.py
openaps/vendors/plugins/add.py
openaps/vendors/plugins/remove.py
openaps/vendors/plugins/show.py
openaps/vendors/plugins/vendor.py
tests/__init__.py
tests/glucose/__init__.py
tests/glucose/test_convert.py
tests/glucose/test_display.py
tests/vendors/__init__.py
tests/vendors/test_medtronic.py