Metadata-Version: 1.1
Name: openaps
Version: 0.1.2
Summary: DIY Open Source Artificial Pancreas System.
Home-page: https://openaps.org/
Author: Ben West
Author-email: bewest+openaps@gmail.com
License: UNKNOWN
Platform: UNKNOWN
Classifier: Development Status :: 3 - Alpha
Classifier: Intended Audience :: Developers
Classifier: Intended Audience :: Science/Research
Classifier: Programming Language :: Python
Classifier: Topic :: Scientific/Engineering
Classifier: Topic :: Software Development :: Libraries
